LICENSE
MANIFEST.in
README.md
setup.cfg
setup.py
dbc_reader/__init__.py
dbc_reader.egg-info/PKG-INFO
dbc_reader.egg-info/SOURCES.txt
dbc_reader.egg-info/dependency_links.txt
dbc_reader.egg-info/requires.txt
dbc_reader.egg-info/top_level.txt
dbc_reader/bin/blast-dbf-darwin
dbc_reader/bin/blast-dbf-linux
dbc_reader/bin/blast-dbf.exe