Metadata-Version: 1.2
Name: dbc-reader
Version: 0.1.2
Summary: Utils classes to read DBC files, a DATASUS compressed DBF files
Home-page: https://github.com/lais-huol/dbc_reader
Author: Kelson da Costa Medeiros
Author-email: kelson.medeiros@lais.huol.ufrn.br
License: MIT
Download-URL: https://github.com/lais-huol/dbc_reader/releases/tag/0.1.2
Keywords: DBF,DBC,reader,datasus
Platform: UNKNOWN
Classifier: Programming Language :: Python :: 3
Classifier: License :: OSI Approved :: MIT License
Classifier: Operating System :: OS Independent
Requires-Python: >=3.7.0
